README.rst
setup.cfg
setup.py
winnow/__init__.py
winnow/core.py
winnow/default_operators.py
winnow/error.py
winnow/relative_dates.py
winnow/sql_prepare.py
winnow/templating.py
winnow/utils.py
winnow/values.py
winnow_filters.egg-info/PKG-INFO
winnow_filters.egg-info/SOURCES.txt
winnow_filters.egg-info/dependency_links.txt
winnow_filters.egg-info/requires.txt
winnow_filters.egg-info/top_level.txt