Metadata-Version: 1.1
Name: winnow-filters
Version: 0.0.5
Summary: Winnow is a framework for server-side filtering of data.
Home-page: https://github.com/bgschiller/winnow
Author: Brian Schiller
Author-email: bgschiller@gmail.com
License: UNKNOWN
Download-URL: https://github.com/bgschiller/winnow/archive/0.0.1.tar.gz
Keywords: sql,jinja2,filters
Platform: UNKNOWN
Classifier: Development Status :: 3 - Alpha
Classifier: License :: OSI Approved :: MIT License
